README.rst
setup.py
pyglet_helper/__init__.py
pyglet_helper/conf.py
pyglet_helper.egg-info/PKG-INFO
pyglet_helper.egg-info/SOURCES.txt
pyglet_helper.egg-info/dependency_links.txt
pyglet_helper.egg-info/requires.txt
pyglet_helper.egg-info/top_level.txt
pyglet_helper/common/__init__.py
pyglet_helper/common/library.txt
pyglet_helper/common/materials.py
pyglet_helper/objects/__init__.py
pyglet_helper/objects/arrow.py
pyglet_helper/objects/axial.py
pyglet_helper/objects/box.py
pyglet_helper/objects/cone.py
pyglet_helper/objects/cylinder.py
pyglet_helper/objects/ellipsoid.py
pyglet_helper/objects/light.py
pyglet_helper/objects/material.py
pyglet_helper/objects/primitive.py
pyglet_helper/objects/pyramid.py
pyglet_helper/objects/rectangular.py
pyglet_helper/objects/renderable.py
pyglet_helper/objects/ring.py
pyglet_helper/objects/sphere.py
pyglet_helper/test/__init__.py
pyglet_helper/test/fake_gl.py
pyglet_helper/util/__init__.py
pyglet_helper/util/color.py
pyglet_helper/util/display_list.py
pyglet_helper/util/linear.py
pyglet_helper/util/quadric.py
pyglet_helper/util/rgba.py
pyglet_helper/util/shader_program.py
pyglet_helper/util/texture.py