Metadata-Version: 1.0
Name: pyglet-helper
Version: 0.0.1
Summary: 3d modelling library
Home-page: http://catherineh.github.io/pyglet_helper/
Author: cholloway
Author-email: milankie@gmail.com
License: UNKNOWN
Platform: UNKNOWN
